[
    {
        "achievement_count": 0,
        "athlete": {
            "id": 2777656,
            "resource_state": 1
        },
        "athlete_count": 1,
        "average_speed": 5.505,
        "average_watts": 93.5,
        "comment_count": 0,
        "commute": false,
        "device_watts": false,
        "distance": 23851.6,
        "elapsed_time": 4646,
        "elev_high": 173.1,
        "elev_low": 75.5,
        "end_latlng": [
            54.47,
            18.49
        ],
        "external_id": "b613378bdd96bfc2b26eada03fd99bbe",
        "flagged": false,
        "from_accepted_tag": false,
        "gear_id": null,
        "has_heartrate": false,
        "has_kudoed": false,
        "id": 73606740,
        "kilojoules": 405.1,
        "kudos_count": 0,
        "location_city": "Gdynia",
        "location_country": "Poland",
        "location_state": "Pomeranian Voivodeship",
        "manual": false,
        "map": {
            "id": "a73606740",
            "resource_state": 2,
            "summary_polyline": "wkmkIs`{oBzErDvLsD~Wz@bB_DvBjC~CkCjH|EfEmCzE??iCngAiEjCz@bBfEfJoZjf@cj@RsNrNf@~M|OzEiEjCwG{Ew[g@nAvBRfEkH~CaQg@kgB_DiJsNwy@f@f@_b@hJnARgThyCwBcBgEjMbBf@gOx`@_Dv[{JvGsDjH?~H~Hbe@kRuDkRbB{EzEsb@zJScBbGrInA~MsDzOcGnAnKvQjHzTrSf^jHjHoA{@wGr]sI{@cGvGcGjRRfOcBrIwVbo@oAbBkCwBk\\{aAkCkHcBR{Jw[_IRwLnP{EwB_I{h@RiC~CRvBuDnFw`@cGcV"
        },
        "max_speed": 20.3,
        "moving_time": 4333,
        "name": "Afternoon Ride",
        "photo_count": 0,
        "pr_count": 0,
        "private": false,
        "resource_state": 2,
        "start_date": "2013-08-10T14:52:10Z",
        "start_date_local": "2013-08-10T16:52:10Z",
        "start_latitude": 54.47,
        "start_latlng": [
            54.47,
            18.49
        ],
        "start_longitude": 18.49,
        "timezone": "(GMT+01:00) Europe/Warsaw",
        "total_elevation_gain": 273.8,
        "total_photo_count": 0,
        "trainer": false,
        "type": "Ride",
        "upload_id": 80361006,
        "utc_offset": 7200.0,
        "workout_type": null
    },
    {
        "achievement_count": 0,
        "athlete": {
            "id": 2777656,
            "resource_state": 1
        },
        "athlete_count": 1,
        "average_speed": 4.218,
        "average_watts": 69.6,
        "comment_count": 0,
        "commute": false,
        "device_watts": false,
        "distance": 51432.7,
        "elapsed_time": 17909,
        "elev_high": 172.0,
        "elev_low": 0.0,
        "end_latlng": [
            54.47,
            18.5
        ],
        "external_id": "da2055a430613ccb2283bb61f4589eca",
        "flagged": false,
        "from_accepted_tag": false,
        "gear_id": null,
        "has_heartrate": false,
        "has_kudoed": false,
        "id": 73822845,
        "kilojoules": 848.2,
        "kudos_count": 0,
        "location_city": "Gdynia",
        "location_country": "Poland",
        "location_state": "Pomeranian Voivodeship",
        "manual": false,
        "map": {
            "id": "a73822845",
            "resource_state": 2,
            "summary_polyline": "gsmkIak|oBnAu{@_g@_g@w`@w|Aw[jf@SsSsIf@{YeYgEpSk\\kWgaAkHwGkH?cV_{@cQvBumAwBxaA_DzT_D_DvBoKkC~HjdAb[bL{r@Swj@nP{@f@sNzOgJf^zY~Mf@SbGvQka@rIzOnF_X_Sg^nd@w[~HwBzTb`@j\\jHby@qDfaAxObuBotBfaA{_BvLsD?sSfO{YwQ~a@f@nP_XjMct@zpA{r@~u@~p@gr@vBfOgEbVfJ~WrIby@jWqDjClPwGfw@k\\roA_DnlAcLzJoZfiB{O|@rD?_Dx@rIju@{pAnKrNrS_Sr]fEnPv`@nx@nKfJvQgEwLh@kH`VwVrIgJfm@k\\rq@os@shBs]rI_SuhArSy`@"
        },
        "max_speed": 23.9,
        "moving_time": 12194,
        "name": "Morning Ride",
        "photo_count": 0,
        "pr_count": 0,
        "private": false,
        "resource_state": 2,
        "start_date": "2013-08-11T07:20:58Z",
        "start_date_local": "2013-08-11T09:20:58Z",
        "start_latitude": 54.47,
        "start_latlng": [
            54.47,
            18.49
        ],
        "start_longitude": 18.49,
        "timezone": "(GMT+01:00) Europe/Warsaw",
        "total_elevation_gain": 460.3,
        "total_photo_count": 0,
        "trainer": false,
        "type": "Ride",
        "upload_id": 80590522,
        "utc_offset": 7200.0,
        "workout_type": null
    },
    {
        "achievement_count": 0,
        "athlete": {
            "id": 2777656,
            "resource_state": 1
        },
        "athlete_count": 1,
        "average_speed": 6.731,
        "average_watts": 97.5,
        "comment_count": 0,
        "commute": false,
        "device_watts": false,
        "distance": 8548.3,
        "elapsed_time": 1319,
        "elev_high": 93.6,
        "elev_low": -0.6,
        "end_latlng": [
            54.53,
            18.53
        ],
        "external_id": "e3943683e65ba39bef975d86a59bf2ad",
        "flagged": false,
        "from_accepted_tag": false,
        "gear_id": null,
        "has_heartrate": false,
        "has_kudoed": false,
        "id": 74047300,
        "kilojoules": 123.8,
        "kudos_count": 0,
        "location_city": "Gdynia",
        "location_country": "Poland",
        "location_state": "Pomeranian Voivodeship",
        "manual": false,
        "map": {
            "id": "a74047300",
            "resource_state": 2,
            "summary_polyline": "cinkIoz~oBwVhJcGcGgJqP_IgE{YnFwGoZkCk\\RsX_N_ScGwBoARoA|O{@P{ToKoAsDkp@sDsXkHSqDkHg@vBmMoA_Dw~@a[we@aDkHvGkMz@oA`D?lF~Mja@"
        },
        "max_speed": 23.3,
        "moving_time": 1270,
        "name": "Morning Ride",
        "photo_count": 0,
        "pr_count": 0,
        "private": false,
        "resource_state": 2,
        "start_date": "2013-08-12T04:58:27Z",
        "start_date_local": "2013-08-12T06:58:27Z",
        "start_latitude": 54.47,
        "start_latlng": [
            54.47,
            18.51
        ],
        "start_longitude": 18.51,
        "timezone": "(GMT+01:00) Europe/Warsaw",
        "total_elevation_gain": 19.4,
        "total_photo_count": 0,
        "trainer": false,
        "type": "Ride",
        "upload_id": 80830748,
        "utc_offset": 7200.0,
        "workout_type": null
    },
    {
        "achievement_count": 0,
        "athlete": {
            "id": 2777656,
            "resource_state": 1
        },
        "athlete_count": 1,
        "average_speed": 5.088,
        "average_watts": 121.3,
        "comment_count": 0,
        "commute": false,
        "device_watts": false,
        "distance": 10730.4,
        "elapsed_time": 2135,
        "elev_high": 122.9,
        "elev_low": -0.9,
        "end_latlng": [
            54.47,
            18.49
        ],
        "external_id": "ce53b9571a8a68666b5f3455b8543174",
        "flagged": false,
        "from_accepted_tag": false,
        "gear_id": null,
        "has_heartrate": false,
        "has_kudoed": false,
        "id": 74125130,
        "kilojoules": 255.8,
        "kudos_count": 0,
        "location_city": "Gdynia",
        "location_country": "Poland",
        "location_state": "Pomeranian Voivodeship",
        "manual": false,
        "map": {
            "id": "a74125130",
            "resource_state": 2,
            "summary_polyline": "wbykIcbcpBcLgh@rI_IbQ_D~HzEnZ?~_AzYz@vB{@nKnK?nAbBg@vGb`@rIn_@f@RzJ~\\~CnAoUzYzc@cB~Mz@ja@~HnZ~WgJjHbLfEh@bQvQzO}EvBgEvGz@bL~M~CjM_Dxo@"
        },
        "max_speed": 12.4,
        "moving_time": 2109,
        "name": "Afternoon Ride",
        "photo_count": 0,
        "pr_count": 0,
        "private": false,
        "resource_state": 2,
        "start_date": "2013-08-12T14:06:12Z",
        "start_date_local": "2013-08-12T16:06:12Z",
        "start_latitude": 54.53,
        "start_latlng": [
            54.53,
            18.53
        ],
        "start_longitude": 18.53,
        "timezone": "(GMT+01:00) Europe/Warsaw",
        "total_elevation_gain": 173.7,
        "total_photo_count": 0,
        "trainer": false,
        "type": "Ride",
        "upload_id": 80913656,
        "utc_offset": 7200.0,
        "workout_type": null
    },
    {
        "achievement_count": 0,
        "athlete": {
            "id": 2777656,
            "resource_state": 1
        },
        "athlete_count": 1,
        "average_speed": 7.634,
        "average_watts": 146.2,
        "comment_count": 0,
        "commute": false,
        "device_watts": false,
        "distance": 31987.8,
        "elapsed_time": 4321,
        "elev_high": 193.4,
        "elev_low": 112.5,
        "end_latlng": [
            54.47,
            18.49
        ],
        "external_id": "4f312a18bbc40d917b1d0c391bd69a0d",
        "flagged": false,
        "from_accepted_tag": false,
        "gear_id": null,
        "has_heartrate": false,
        "has_kudoed": false,
        "id": 77183932,
        "kilojoules": 612.5,
        "kudos_count": 0,
        "location_city": "Gdynia",
        "location_country": "Poland",
        "location_state": "Pomeranian Voivodeship",
        "manual": false,
        "map": {
            "id": "a77183932",
            "resource_state": 2,
            "summary_polyline": "w_nkI_dyoB_DfTcQ~f@StNbGxY?tI{ExT_DfEsDbLcBjRRnK{EdVwLtVSrSoFnd@sDz@cG_DgEfTwLzY{EjRcQnZoFz@wB~H_{@|r@{Jd^kR~a@RzJ_Db`@gEdLsD|CoAfO~Hnn@~Ce@nKdJfEr{@fYja@fJrD~CvGzOjHzJpKbQhf@jWn_@~CjWjHkHr]vV~W_DbBgEv[f@vQkCb[{c@fYyJvGdEzOxBgEma@bBcLbGf@z@oUoAwQvB{OzJw`@nAwQg@cLcQct@cLwo@be@nP~a@f@nFoFjCec@nA}dBkCgY?wGcL_S{EsNwL}u@wV}r@od@yfAcBqAwGnPkCcBgm@oeB{E}CsDRsIbQsDlAkCaBkHug@?yEjRgm@~C}T"
        },
        "max_speed": 34.1,
        "moving_time": 4190,
        "name": "Evening Ride",
        "photo_count": 0,
        "pr_count": 0,
        "private": false,
        "resource_state": 2,
        "start_date": "2013-08-24T16:27:05Z",
        "start_date_local": "2013-08-24T18:27:05Z",
        "start_latitude": 54.47,
        "start_latlng": [
            54.47,
            18.49
        ],
        "start_longitude": 18.49,
        "timezone": "(GMT+01:00) Europe/Warsaw",
        "total_elevation_gain": 211.7,
        "total_photo_count": 0,
        "trainer": false,
        "type": "Ride",
        "upload_id": 84138824,
        "utc_offset": 7200.0,
        "workout_type": null
    },
    {
        "achievement_count": 2,
        "athlete": {
            "id": 2777656,
            "resource_state": 1
        },
        "athlete_count": 1,
        "average_speed": 7.167,
        "average_watts": 140.9,
        "comment_count": 0,
        "commute": false,
        "device_watts": false,
        "distance": 117136.0,
        "elapsed_time": 19751,
        "elev_high": 242.4,
        "elev_low": 83.2,
        "end_latlng": [
            54.47,
            18.49
        ],
        "external_id": "c4e88c2b0f67e199494396a3a9dc4bca",
        "flagged": false,
        "from_accepted_tag": false,
        "gear_id": null,
        "has_heartrate": false,
        "has_kudoed": false,
        "id": 77361430,
        "kilojoules": 2303.0,
        "kudos_count": 0,
        "location_city": "Gdynia",
        "location_country": "Poland",
        "location_state": "Pomeranian Voivodeship",
        "manual": false,
        "map": {
            "id": "a77361430",
            "resource_state": 2,
            "summary_polyline": "o~mkIgeyoBkWz|@bGxt@kp@lpDwL{@od@drAgkAlgAc[t{@gYtaBfc@d~@_Dha@zkAjsAfm@zzAni@zTbmAmUvo@co@zY~Hn_@t~@kRvLz@~Wrq@yc@nFu]ns@?fw@~lBfkAxt@~f@|oCzc@z^rfCxLksAjpEkk@lzDfT_IjW`oAf^`|Fn_@sSjk@jf@j_AgOjf@b`@{JhlCwrAhnAg^aLRfaA{^hz@_]f}BfEb[gm@bmAfT~u@sq@vkBbGj\\oKb[be@pbAgJpv@kiAwy@oZ~p@{YbLw|AoP_v@yr@g@qUsoA|^we@erA{EoqAokDkzJoZ{}Bos@k_AcBcdC~p@ofDvGcrAce@wQ{}Bzw@cVwo@saCsoAcy@uhA{c@uD{uAs~AnAw`@jdAobAni@sIj}AspCrwBjf@v~@sjAjCgfAve@kqB~u@c[fr@mbAgm@acBsjAwhAsSw_CzYsl@oFsXzT{r@ffAkdAby@c|AbB_`Av[sb@jR{fAsI_v@~W_`A"
        },
        "max_speed": 20.8,
        "moving_time": 16343,
        "name": "Morning Ride",
        "photo_count": 0,
        "pr_count": 1,
        "private": false,
        "resource_state": 2,
        "start_date": "2013-08-25T06:00:25Z",
        "start_date_local": "2013-08-25T08:00:25Z",
        "start_latitude": 54.47,
        "start_latlng": [
            54.47,
            18.49
        ],
        "start_longitude": 18.49,
        "timezone": "(GMT+01:00) Europe/Warsaw",
        "total_elevation_gain": 1111.8,
        "total_photo_count": 0,
        "trainer": false,
        "type": "Ride",
        "upload_id": 84326412,
        "utc_offset": 7200.0,
        "workout_type": null
    },
    {
        "achievement_count": 0,
        "athlete": {
            "id": 2777656,
            "resource_state": 1
        },
        "athlete_count": 1,
        "average_speed": 6.73,
        "average_watts": 81.5,
        "comment_count": 0,
        "commute": false,
        "device_watts": false,
        "distance": 11212.0,
        "elapsed_time": 1666,
        "elev_high": 125.0,
        "elev_low": -1.1,
        "end_latlng": [
            54.53,
            18.53
        ],
        "external_id": "2f705c8c8918afe3df2baa6c880b62c5",
        "flagged": false,
        "from_accepted_tag": false,
        "gear_id": null,
        "has_heartrate": false,
        "has_kudoed": false,
        "id": 77576035,
        "kilojoules": 135.8,
        "kudos_count": 0,
        "location_city": "Gdynia",
        "location_country": "Poland",
        "location_state": "Pomeranian Voivodeship",
        "manual": false,
        "map": {
            "id": "a77576035",
            "resource_state": 2,
            "summary_polyline": "wpmkI}b|oB{@cGf@mWrDuVSaDgOsSc[{Yw[_tA{E{JsXrg@SkMgJQkHeGgEyJRkHcLkHvBeG{^nAwBfOgm@_DoUwGwB_Df@wBwGRRaGbBeBg@kCcGRgEsD_{@oZsSvBcL{E{EtDsIx@gEpF?pDnK~a@g@z@"
        },
        "max_speed": 15.7,
        "moving_time": 1666,
        "name": "Morning Ride",
        "photo_count": 0,
        "pr_count": 0,
        "private": false,
        "resource_state": 2,
        "start_date": "2013-08-26T04:54:20Z",
        "start_date_local": "2013-08-26T06:54:20Z",
        "start_latitude": 54.47,
        "start_latlng": [
            54.47,
            18.49
        ],
        "start_longitude": 18.49,
        "timezone": "(GMT+01:00) Europe/Warsaw",
        "total_elevation_gain": 29.7,
        "total_photo_count": 0,
        "trainer": false,
        "type": "Ride",
        "upload_id": 84553618,
        "utc_offset": 7200.0,
        "workout_type": null
    },
    {
        "achievement_count": 0,
        "athlete": {
            "id": 2777656,
            "resource_state": 1
        },
        "athlete_count": 1,
        "average_speed": 6.082,
        "average_watts": 146.7,
        "comment_count": 0,
        "commute": false,
        "device_watts": false,
        "distance": 11336.1,
        "elapsed_time": 1963,
        "elev_high": 124.5,
        "elev_low": -1.1,
        "end_latlng": [
            54.47,
            18.49
        ],
        "external_id": "301d097789b484c3503ed3a642b5f59f",
        "flagged": false,
        "from_accepted_tag": false,
        "gear_id": null,
        "has_heartrate": false,
        "has_kudoed": false,
        "id": 77667564,
        "kilojoules": 273.5,
        "kudos_count": 0,
        "location_city": "Gdynia",
        "location_country": "Poland",
        "location_state": "Pomeranian Voivodeship",
        "manual": false,
        "map": {
            "id": "a77667564",
            "resource_state": 2,
            "summary_polyline": "c}xkIcbcpBgEwG{J{^~CsDjMkC~C{EzJjHzOcBbe@rIbBrDbe@~M{@vLnKh@nAdJ{@oArNbGzr@rDf@|EvVdJnFsDoAcQvBwBbLzY~HjHrD?g@fEjC~MjWod@bBwGrIzOb[fpAfh@be@f@tIkCxr@"
        },
        "max_speed": 16.3,
        "moving_time": 1864,
        "name": "Afternoon Ride",
        "photo_count": 0,
        "pr_count": 0,
        "private": false,
        "resource_state": 2,
        "start_date": "2013-08-26T14:02:40Z",
        "start_date_local": "2013-08-26T16:02:40Z",
        "start_latitude": 54.53,
        "start_latlng": [
            54.53,
            18.53
        ],
        "start_longitude": 18.53,
        "timezone": "(GMT+01:00) Europe/Warsaw",
        "total_elevation_gain": 169.5,
        "total_photo_count": 0,
        "trainer": false,
        "type": "Ride",
        "upload_id": 84650557,
        "utc_offset": 7200.0,
        "workout_type": null
    },
    {
        "achievement_count": 1,
        "athlete": {
            "id": 2777656,
            "resource_state": 1
        },
        "athlete_count": 1,
        "average_speed": 4.932,
        "average_watts": 92.1,
        "comment_count": 0,
        "commute": false,
        "device_watts": false,
        "distance": 15078.6,
        "elapsed_time": 4839,
        "elev_high": 155.3,
        "elev_low": 101.2,
        "end_latlng": [
            54.47,
            18.49
        ],
        "external_id": "0f678eeab1164ab229e15e5b8cd3edf4",
        "flagged": false,
        "from_accepted_tag": false,
        "gear_id": null,
        "has_heartrate": false,
        "has_kudoed": false,
        "id": 77708974,
        "kilojoules": 281.7,
        "kudos_count": 0,
        "location_city": "Gdynia",
        "location_country": "Poland",
        "location_state": "Pomeranian Voivodeship",
        "manual": false,
        "map": {
            "id": "a77708974",
            "resource_state": 2,
            "summary_polyline": "gsmkIak|oBnA}@vBce@bBTkM`BbG?f@wBgE~u@kCzJoA~WsDrNkHoAwBnPR|T{@xEkH~\\cG`IkCxJkHzJ_NiC_NjH{EdEcGrNwLvLg@~CkR|OgT`BoFzJ_DnPsDnAwBjH_I??|^fEdh@vBnKf@vQkCdBkCiEwBRfJnAbBwBwBka@wGod@vBc[fJpAf@qFjM_XjC}CbGSbGeGf@{ErD?~MsIjCsDRcGfOsI~CyEf@qFrv@sl@vGwQg@_I"
        },
        "max_speed": 15.0,
        "moving_time": 3057,
        "name": "Afternoon Ride",
        "photo_count": 0,
        "pr_count": 0,
        "private": false,
        "resource_state": 2,
        "start_date": "2013-08-26T15:57:36Z",
        "start_date_local": "2013-08-26T17:57:36Z",
        "start_latitude": 54.47,
        "start_latlng": [
            54.47,
            18.49
        ],
        "start_longitude": 18.49,
        "timezone": "(GMT+01:00) Europe/Warsaw",
        "total_elevation_gain": 163.6,
        "total_photo_count": 0,
        "trainer": false,
        "type": "Ride",
        "upload_id": 84695301,
        "utc_offset": 7200.0,
        "workout_type": null
    },
    {
        "achievement_count": 0,
        "athlete": {
            "id": 2777656,
            "resource_state": 1
        },
        "athlete_count": 1,
        "average_speed": 6.185,
        "average_watts": 77.1,
        "comment_count": 0,
        "commute": false,
        "device_watts": false,
        "distance": 10507.5,
        "elapsed_time": 1765,
        "elev_high": 122.4,
        "elev_low": -0.9,
        "end_latlng": [
            54.53,
            18.54
        ],
        "external_id": "22d4ca2028b3cda67a1df39a7583e3ae",
        "flagged": false,
        "from_accepted_tag": false,
        "gear_id": null,
        "has_heartrate": false,
        "has_kudoed": false,
        "id": 77834092,
        "kilojoules": 130.9,
        "kudos_count": 0,
        "location_city": "Gdynia",
        "location_country": "Poland",
        "location_state": "Pomeranian Voivodeship",
        "manual": false,
        "map": {
            "id": "a77834092",
            "resource_state": 2,
            "summary_polyline": "gsmkIak|oBjCaq@oA{JkRcQ_D?_S|J{J}EsIsNwGwBcB{EgEfEcQjCwGc[_D_]RoUoKwQoFoFwBg@wBpPgYiJoA{E{m@wBgTcGg@_I_I?z@cL{@oAobAq]kWlA_NcGkCtDcLhCgEnFbLnd@"
        },
        "max_speed": 11.9,
        "moving_time": 1699,
        "name": "Morning Ride",
        "photo_count": 0,
        "pr_count": 0,
        "private": false,
        "resource_state": 2,
        "start_date": "2013-08-27T04:51:34Z",
        "start_date_local": "2013-08-27T06:51:34Z",
        "start_latitude": 54.47,
        "start_latlng": [
            54.47,
            18.49
        ],
        "start_longitude": 18.49,
        "timezone": "(GMT+01:00) Europe/Warsaw",
        "total_elevation_gain": 41.8,
        "total_photo_count": 0,
        "trainer": false,
        "type": "Ride",
        "upload_id": 84828829,
        "utc_offset": 7200.0,
        "workout_type": null
    },
    {
        "achievement_count": 0,
        "athlete": {
            "id": 2777656,
            "resource_state": 1
        },
        "athlete_count": 1,
        "average_speed": 4.891,
        "average_watts": 108.7,
        "comment_count": 0,
        "commute": false,
        "device_watts": false,
        "distance": 10412.8,
        "elapsed_time": 2188,
        "elev_high": 122.3,
        "elev_low": -1.0,
        "end_latlng": [
            54.47,
            18.49
        ],
        "external_id": "bebde1772724d05351a671f08ad64927",
        "flagged": false,
        "from_accepted_tag": false,
        "gear_id": null,
        "has_heartrate": false,
        "has_kudoed": false,
        "id": 77927175,
        "kilojoules": 231.5,
        "kudos_count": 0,
        "location_city": "Gdynia",
        "location_country": "Poland",
        "location_state": "Pomeranian Voivodeship",
        "manual": false,
        "map": {
            "id": "a77927175",
            "resource_state": 2,
            "summary_polyline": "cbykIoacpBwL{h@fEgEvLcBjCsDzJzEnZSbcAj\\g@jMrITnA~HjRlFnn@~Cz@hEfYdJjC{ObGtDvLjR?xObBrXfJjf@jWwGz@nFjHbBvG~MfOhEbQqKrDf@bQzObBdLkCbo@"
        },
        "max_speed": 8.7,
        "moving_time": 2129,
        "name": "Afternoon Ride",
        "photo_count": 0,
        "pr_count": 0,
        "private": false,
        "resource_state": 2,
        "start_date": "2013-08-27T15:00:05Z",
        "start_date_local": "2013-08-27T17:00:05Z",
        "start_latitude": 54.53,
        "start_latlng": [
            54.53,
            18.53
        ],
        "start_longitude": 18.53,
        "timezone": "(GMT+01:00) Europe/Warsaw",
        "total_elevation_gain": 161.6,
        "total_photo_count": 0,
        "trainer": false,
        "type": "Ride",
        "upload_id": 84926826,
        "utc_offset": 7200.0,
        "workout_type": null
    },
    {
        "achievement_count": 0,
        "athlete": {
            "id": 2777656,
            "resource_state": 1
        },
        "athlete_count": 1,
        "average_speed": 5.882,
        "average_watts": 76.5,
        "comment_count": 0,
        "commute": false,
        "device_watts": false,
        "distance": 10517.9,
        "elapsed_time": 1852,
        "elev_high": 122.7,
        "elev_low": -1.0,
        "end_latlng": [
            54.53,
            18.54
        ],
        "external_id": "f686acc35dbc32006530857778fb5b2e",
        "flagged": false,
        "from_accepted_tag": false,
        "gear_id": null,
        "has_heartrate": false,
        "has_kudoed": false,
        "id": 78104278,
        "kilojoules": 136.8,
        "kudos_count": 0,
        "location_city": "Gdynia",
        "location_country": "Poland",
        "location_state": "Pomeranian Voivodeship",
        "manual": false,
        "map": {
            "id": "a78104278",
            "resource_state": 2,
            "summary_polyline": "srmkI{i|oBjC}p@wBeLwQcQsDSoPzJcL_DsI_N_I_DwBsDcVbGsIgh@cBw[z@cGsNmUcG}E_D|OgYuISkCcB{@gm@_DsSoFg@sIkHRz@wL_eAy^oFSoFlASnAoU_IgEtDoKlAgEbGnKve@"
        },
        "max_speed": 15.0,
        "moving_time": 1788,
        "name": "Morning Ride",
        "photo_count": 0,
        "pr_count": 0,
        "private": false,
        "resource_state": 2,
        "start_date": "2013-08-28T04:53:54Z",
        "start_date_local": "2013-08-28T06:53:54Z",
        "start_latitude": 54.47,
        "start_latlng": [
            54.47,
            18.49
        ],
        "start_longitude": 18.49,
        "timezone": "(GMT+01:00) Europe/Warsaw",
        "total_elevation_gain": 33.7,
        "total_photo_count": 0,
        "trainer": false,
        "type": "Ride",
        "upload_id": 85114614,
        "utc_offset": 7200.0,
        "workout_type": null
    },
    {
        "achievement_count": 0,
        "athlete": {
            "id": 2777656,
            "resource_state": 1
        },
        "athlete_count": 1,
        "average_speed": 5.385,
        "average_watts": 122.2,
        "comment_count": 0,
        "commute": false,
        "device_watts": false,
        "distance": 10586.8,
        "elapsed_time": 2271,
        "elev_high": 122.5,
        "elev_low": -1.1,
        "end_latlng": [
            54.47,
            18.49
        ],
        "external_id": "1a24c06e0cf45808c32ed95fa81811cd",
        "flagged": false,
        "from_accepted_tag": false,
        "gear_id": null,
        "has_heartrate": false,
        "has_kudoed": false,
        "id": 78196835,
        "kilojoules": 240.2,
        "kudos_count": 0,
        "location_city": "Gdynia",
        "location_country": "Poland",
        "location_state": "Pomeranian Voivodeship",
        "manual": false,
        "map": {
            "id": "a78196835",
            "resource_state": 2,
            "summary_polyline": "cbykIkccpBwLkf@fE{EvLcBjCsDzJzEnZSvcAj\\{@`NrI?z@~HzTjHrl@tBz@hEzYdJbBoPnARrSbVSzT~Cja@jHnZzJ{@zJoFnAzEvGvBnFvLbQpFjMqFvB_DrDf@vQnPvBjRvBRgE|@cBve@"
        },
        "max_speed": 9.3,
        "moving_time": 1966,
        "name": "Afternoon Ride",
        "photo_count": 0,
        "pr_count": 0,
        "private": false,
        "resource_state": 2,
        "start_date": "2013-08-28T14:59:10Z",
        "start_date_local": "2013-08-28T16:59:10Z",
        "start_latitude": 54.53,
        "start_latlng": [
            54.53,
            18.54
        ],
        "start_longitude": 18.54,
        "timezone": "(GMT+01:00) Europe/Warsaw",
        "total_elevation_gain": 161.8,
        "total_photo_count": 0,
        "trainer": false,
        "type": "Ride",
        "upload_id": 85211108,
        "utc_offset": 7200.0,
        "workout_type": null
    },
    {
        "achievement_count": 0,
        "athlete": {
            "id": 2777656,
            "resource_state": 1
        },
        "athlete_count": 1,
        "average_speed": 6.06,
        "average_watts": 79.2,
        "comment_count": 0,
        "commute": false,
        "device_watts": false,
        "distance": 10526.8,
        "elapsed_time": 1737,
        "elev_high": 122.4,
        "elev_low": -0.9,
        "end_latlng": [
            54.53,
            18.54
        ],
        "external_id": "d69b4535d0523f36991301eb4734fcf6",
        "flagged": false,
        "from_accepted_tag": false,
        "gear_id": null,
        "has_heartrate": false,
        "has_kudoed": false,
        "id": 78359669,
        "kilojoules": 137.6,
        "kudos_count": 0,
        "location_city": "Gdynia",
        "location_country": "Poland",
        "location_state": "Pomeranian Voivodeship",
        "manual": false,
        "map": {
            "id": "a78359669",
            "resource_state": 2,
            "summary_polyline": "gsmkIoj|oB~C_q@wBoKcQoPsDg@kC~CwLfE_NwBkHuLkHuDSiCoAqAwVvGgJ_l@oAgOf@}RcLwQkHqF{@?kC|O_XiJcBgEwt@{EwL}CoA_IkHUnAwL_eAy^sSpDkHoFkHcBoPbGsDnFzJve@"
        },
        "max_speed": 12.8,
        "moving_time": 1737,
        "name": "Morning Ride",
        "photo_count": 0,
        "pr_count": 0,
        "private": false,
        "resource_state": 2,
        "start_date": "2013-08-29T04:54:31Z",
        "start_date_local": "2013-08-29T06:54:31Z",
        "start_latitude": 54.47,
        "start_latlng": [
            54.47,
            18.49
        ],
        "start_longitude": 18.49,
        "timezone": "(GMT+01:00) Europe/Warsaw",
        "total_elevation_gain": 42.2,
        "total_photo_count": 0,
        "trainer": false,
        "type": "Ride",
        "upload_id": 85383059,
        "utc_offset": 7200.0,
        "workout_type": null
    },
    {
        "achievement_count": 2,
        "athlete": {
            "id": 2777656,
            "resource_state": 1
        },
        "athlete_count": 3,
        "average_speed": 5.196,
        "average_watts": 110.0,
        "comment_count": 0,
        "commute": false,
        "device_watts": false,
        "distance": 21522.1,
        "elapsed_time": 5605,
        "elev_high": 163.9,
        "elev_low": 73.3,
        "end_latlng": [
            54.47,
            18.49
        ],
        "external_id": "31c419b51f03eb8af9f9a67ce92347ee",
        "flagged": false,
        "from_accepted_tag": false,
        "gear_id": null,
        "has_heartrate": false,
        "has_kudoed": false,
        "id": 78480972,
        "kilojoules": 455.8,
        "kudos_count": 0,
        "location_city": "Gdynia",
        "location_country": "Poland",
        "location_state": "Pomeranian Voivodeship",
        "manual": false,
        "map": {
            "id": "a78480972",
            "resource_state": 2,
            "summary_polyline": "wlokI{a{oBsIbQsNnKoPwGoP{TcBn_@gJvLkHsDoKcQgEkCgEmK{ER_SmHoUlHkMeG_]n_@{ExBcGpNsIzJgJfEgTfT{EjMoFvGoAvG_NrI_Nlk@_Nx@{@cGjCmAzJwQkCmMvQf@fOoKz@wGnAz@vBnFkCjCcBwB_DbGkCrIf@`N{@aDgEoAoF|EvGuXvLcG~CoKzE{EnFkM~a@s]rIcLnAcG~MkH~H`DbGhMnPjp@vGvLvBfYfOjCwB~p@jCnn@nFbBvLmPrIkRjWqKzTsSrS~HvV~R~H{@bLlM~HuNzEwQS_N{Oku@nF}H~Hy`@"
        },
        "max_speed": 15.0,
        "moving_time": 4142,
        "name": "Evening Ride",
        "photo_count": 0,
        "pr_count": 0,
        "private": false,
        "resource_state": 2,
        "start_date": "2013-08-29T16:15:16Z",
        "start_date_local": "2013-08-29T18:15:16Z",
        "start_latitude": 54.47,
        "start_latlng": [
            54.47,
            18.49
        ],
        "start_longitude": 18.49,
        "timezone": "(GMT+01:00) Europe/Warsaw",
        "total_elevation_gain": 308.3,
        "total_photo_count": 0,
        "trainer": false,
        "type": "Ride",
        "upload_id": 85511381,
        "utc_offset": 7200.0,
        "workout_type": null
    },
    {
        "achievement_count": 0,
        "athlete": {
            "id": 2777656,
            "resource_state": 1
        },
        "athlete_count": 1,
        "average_speed": 5.255,
        "average_watts": 121.3,
        "comment_count": 0,
        "commute": false,
        "device_watts": false,
        "distance": 10530.9,
        "elapsed_time": 2152,
        "elev_high": 122.3,
        "elev_low": -1.2,
        "end_latlng": [
            54.47,
            18.49
        ],
        "external_id": "18e8fdb1ec1110e531996be9416117c5",
        "flagged": false,
        "from_accepted_tag": false,
        "gear_id": null,
        "has_heartrate": false,
        "has_kudoed": false,
        "id": 78688396,
        "kilojoules": 243.1,
        "kudos_count": 0,
        "location_city": "Gdynia",
        "location_country": "Poland",
        "location_state": "Pomeranian Voivodeship",
        "manual": false,
        "map": {
            "id": "a78688396",
            "resource_state": 2,
            "summary_polyline": "g`ykI{`cpB_N{h@rD{EvLcBjCsDzJzEr]R~_Av[SlM~H?bB~HrSjHzm@tBRtDfYlKvBcQjCz@jRjWoAvLnAzOjC`XvGpXf@zJwBnZwQzr@{@|Oz@vQfT`[zO`IzE}@jMcQfE_N"
        },
        "max_speed": 10.0,
        "moving_time": 2004,
        "name": "Afternoon Ride",
        "photo_count": 0,
        "pr_count": 0,
        "private": false,
        "resource_state": 2,
        "start_date": "2013-08-30T14:56:31Z",
        "start_date_local": "2013-08-30T16:56:31Z",
        "start_latitude": 54.53,
        "start_latlng": [
            54.53,
            18.53
        ],
        "start_longitude": 18.53,
        "timezone": "(GMT+01:00) Europe/Warsaw",
        "total_elevation_gain": 157.3,
        "total_photo_count": 0,
        "trainer": false,
        "type": "Ride",
        "upload_id": 85731041,
        "utc_offset": 7200.0,
        "workout_type": null
    },
    {
        "achievement_count": 0,
        "athlete": {
            "id": 2777656,
            "resource_state": 1
        },
        "athlete_count": 1,
        "average_speed": 5.486,
        "average_watts": 72.0,
        "comment_count": 0,
        "commute": false,
        "device_watts": false,
        "distance": 5184.5,
        "elapsed_time": 945,
        "elev_high": 121.9,
        "elev_low": 39.4,
        "end_latlng": [
            54.49,
            18.53
        ],
        "external_id": "71ef2aab3b8f36a218ca78e4be2a099f",
        "flagged": false,
        "from_accepted_tag": false,
        "gear_id": null,
        "has_heartrate": false,
        "has_kudoed": false,
        "id": 78701436,
        "kilojoules": 68.0,
        "kudos_count": 0,
        "location_city": "Gdynia",
        "location_country": "Poland",
        "location_state": "Pomeranian Voivodeship",
        "manual": false,
        "map": {
            "id": "a78701436",
            "resource_state": 2,
            "summary_polyline": "clokIob{oBgEnKwGrIwLvGsNwG_I{JsIcQ{@cLRcLjRku@jCg^g@gJkHs]_Dw[RaVwLkRkHqF{E|O"
        },
        "max_speed": 11.9,
        "moving_time": 945,
        "name": "Evening Ride",
        "photo_count": 0,
        "pr_count": 0,
        "private": false,
        "resource_state": 2,
        "start_date": "2013-08-30T16:11:26Z",
        "start_date_local": "2013-08-30T18:11:26Z",
        "start_latitude": 54.47,
        "start_latlng": [
            54.47,
            18.49
        ],
        "start_longitude": 18.49,
        "timezone": "(GMT+01:00) Europe/Warsaw",
        "total_elevation_gain": 14.0,
        "total_photo_count": 0,
        "trainer": false,
        "type": "Ride",
        "upload_id": 85744491,
        "utc_offset": 7200.0,
        "workout_type": null
    },
    {
        "achievement_count": 2,
        "athlete": {
            "id": 2777656,
            "resource_state": 1
        },
        "athlete_count": 1,
        "average_speed": 3.579,
        "average_watts": 71.6,
        "comment_count": 0,
        "commute": false,
        "device_watts": false,
        "distance": 7044.4,
        "elapsed_time": 1968,
        "elev_high": 122.1,
        "elev_low": 29.2,
        "end_latlng": [
            54.47,
            18.49
        ],
        "external_id": "1304280187323cc4d5c84ee518a99b2b",
        "flagged": false,
        "from_accepted_tag": false,
        "gear_id": null,
        "has_heartrate": false,
        "has_kudoed": false,
        "id": 78765813,
        "kilojoules": 140.9,
        "kudos_count": 0,
        "location_city": "Gdynia",
        "location_country": "Poland",
        "location_state": "Pomeranian Voivodeship",
        "manual": false,
        "map": {
            "id": "a78765813",
            "resource_state": 2,
            "summary_polyline": "{~tkIa}bpBnP`Gbo@vBnAkM~\\{@z@z@?jCjHbGS~HrDjHfJ~HbL?RrIbVw`@zEbLb[zpArg@ve@z@rIkCxo@"
        },
        "max_speed": 9.1,
        "moving_time": 1968,
        "name": "Night Ride",
        "photo_count": 0,
        "pr_count": 0,
        "private": false,
        "resource_state": 2,
        "start_date": "2013-08-30T21:10:59Z",
        "start_date_local": "2013-08-30T23:10:59Z",
        "start_latitude": 54.51,
        "start_latlng": [
            54.51,
            18.53
        ],
        "start_longitude": 18.53,
        "timezone": "(GMT+01:00) Europe/Warsaw",
        "total_elevation_gain": 125.6,
        "total_photo_count": 0,
        "trainer": false,
        "type": "Ride",
        "upload_id": 85813141,
        "utc_offset": 7200.0,
        "workout_type": null
    },
    {
        "achievement_count": 0,
        "athlete": {
            "id": 2777656,
            "resource_state": 1
        },
        "athlete_count": 1,
        "average_speed": 5.2,
        "average_watts": 57.8,
        "comment_count": 0,
        "commute": false,
        "device_watts": false,
        "distance": 10311.5,
        "elapsed_time": 1983,
        "elev_high": 121.6,
        "elev_low": -1.1,
        "end_latlng": [
            54.53,
            18.54
        ],
        "external_id": "b88e9f2a816cbdfc105e7e3ee19befc3",
        "flagged": false,
        "from_accepted_tag": false,
        "gear_id": null,
        "has_heartrate": false,
        "has_kudoed": false,
        "id": 78837767,
        "kilojoules": 114.6,
        "kudos_count": 0,
        "location_city": "Gdynia",
        "location_country": "Poland",
        "location_state": "Pomeranian Voivodeship",
        "manual": false,
        "map": {
            "id": "a78837767",
            "resource_state": 2,
            "summary_polyline": "clokIwc{oB{ErNwQrN_NsD{OgOwBcG_DaVRaIrD_NnAwLrI_XjC{^sNseARoUkRsXkC{@kCrNsXkHoAgE_q@sDoP{Eg@uGsIi@z@_Nw~@w[s]SkM{EkC`DoK`BgEnFfJjf@"
        },
        "max_speed": 15.5,
        "moving_time": 1983,
        "name": "Morning Ride",
        "photo_count": 0,
        "pr_count": 0,
        "private": false,
        "resource_state": 2,
        "start_date": "2013-08-31T07:37:52Z",
        "start_date_local": "2013-08-31T09:37:52Z",
        "start_latitude": 54.47,
        "start_latlng": [
            54.47,
            18.49
        ],
        "start_longitude": 18.49,
        "timezone": "(GMT+01:00) Europe/Warsaw",
        "total_elevation_gain": 13.4,
        "total_photo_count": 0,
        "trainer": false,
        "type": "Ride",
        "upload_id": 85889257,
        "utc_offset": 7200.0,
        "workout_type": null
    },
    {
        "achievement_count": 0,
        "athlete": {
            "id": 2777656,
            "resource_state": 1
        },
        "athlete_count": 1,
        "average_speed": 3.883,
        "average_watts": 70.3,
        "comment_count": 0,
        "commute": false,
        "device_watts": false,
        "distance": 9082.4,
        "elapsed_time": 2373,
        "elev_high": 135.9,
        "elev_low": 23.6,
        "end_latlng": [
            54.42,
            18.56
        ],
        "external_id": "7419ce4124e8a60fe48a62da4f21a4d8",
        "flagged": false,
        "from_accepted_tag": false,
        "gear_id": null,
        "has_heartrate": false,
        "has_kudoed": false,
        "id": 79106144,
        "kilojoules": 164.3,
        "kudos_count": 0,
        "location_city": "Gdynia",
        "location_country": "Poland",
        "location_state": "Pomeranian Voivodeship",
        "manual": false,
        "map": {
            "id": "a79106144",
            "resource_state": 2,
            "summary_polyline": "gsmkIoj|oBnAe@~Cir@jM{@vGoFvGeOvGaIrIgEvG{OfE}CjCuSf@yY{@}JbB_Ig@sSfERz@iMrIeVzJkRrDwQjHkC~CnAnF{EzEc`@bGoUbo@_Ive@yOfEkHjCqAfErDrISoA~Mf@jHbGh@fEaD"
        },
        "max_speed": 12.2,
        "moving_time": 2339,
        "name": "Morning Ride",
        "photo_count": 0,
        "pr_count": 0,
        "private": false,
        "resource_state": 2,
        "start_date": "2013-09-01T08:31:13Z",
        "start_date_local": "2013-09-01T10:31:13Z",
        "start_latitude": 54.47,
        "start_latlng": [
            54.47,
            18.49
        ],
        "start_longitude": 18.49,
        "timezone": "(GMT+01:00) Europe/Warsaw",
        "total_elevation_gain": 113.1,
        "total_photo_count": 0,
        "trainer": false,
        "type": "Ride",
        "upload_id": 86174231,
        "utc_offset": 7200.0,
        "workout_type": null
    },
    {
        "achievement_count": 0,
        "athlete": {
            "id": 2777656,
            "resource_state": 1
        },
        "athlete_count": 1,
        "average_speed": 5.371,
        "average_watts": 63.3,
        "comment_count": 0,
        "commute": false,
        "device_watts": false,
        "distance": 10474.1,
        "elapsed_time": 1950,
        "elev_high": 122.4,
        "elev_low": -1.0,
        "end_latlng": [
            54.53,
            18.54
        ],
        "external_id": "78ad956291474d61c458f96996830ab9",
        "flagged": false,
        "from_accepted_tag": false,
        "gear_id": null,
        "has_heartrate": false,
        "has_kudoed": false,
        "id": 79634771,
        "kilojoules": 123.4,
        "kudos_count": 0,
        "location_city": "Gdynia",
        "location_country": "Poland",
        "location_state": "Pomeranian Voivodeship",
        "manual": false,
        "map": {
            "id": "a79634771",
            "resource_state": 2,
            "summary_polyline": "gsmkIoj|oBjCuo@cByLsNqNcGeBkC~CcLzEsNkCwGsNwGwBsD{EoUvGwGw[_Dk\\RuVoKcQoFiEwBg@kChO_X_Ig@aDoA{@sl@kCgTcG{@_IkH?RkMwcAs]wVnAsNkH_DtDoKtBgEnFnKve@"
        },
        "max_speed": 11.4,
        "moving_time": 1950,
        "name": "Morning Ride",
        "photo_count": 0,
        "pr_count": 0,
        "private": false,
        "resource_state": 2,
        "start_date": "2013-09-03T04:55:02Z",
        "start_date_local": "2013-09-03T06:55:02Z",
        "start_latitude": 54.47,
        "start_latlng": [
            54.47,
            18.49
        ],
        "start_longitude": 18.49,
        "timezone": "(GMT+01:00) Europe/Warsaw",
        "total_elevation_gain": 40.7,
        "total_photo_count": 0,
        "trainer": false,
        "type": "Ride",
        "upload_id": 86735976,
        "utc_offset": 7200.0,
        "workout_type": null
    },
    {
        "achievement_count": 0,
        "athlete": {
            "id": 2777656,
            "resource_state": 1
        },
        "athlete_count": 1,
        "average_speed": 4.558,
        "average_watts": 100.9,
        "comment_count": 0,
        "commute": false,
        "device_watts": false,
        "distance": 10502.0,
        "elapsed_time": 2405,
        "elev_high": 122.5,
        "elev_low": -1.0,
        "end_latlng": [
            54.47,
            18.49
        ],
        "external_id": "7b0e5d292b414b627baad8b3d97d7dea",
        "flagged": false,
        "from_accepted_tag": false,
        "gear_id": null,
        "has_heartrate": false,
        "has_kudoed": false,
        "id": 79715360,
        "kilojoules": 232.5,
        "kudos_count": 0,
        "location_city": "Gdynia",
        "location_country": "Poland",
        "location_state": "Pomeranian Voivodeship",
        "manual": false,
        "map": {
            "id": "a79715360",
            "resource_state": 2,
            "summary_polyline": "{`ykIg`cpB_Noi@zE{EbLoAzEgEjHfEb[f@bcAv[{@vLfJTbBtB?rDjRzJfm@f@z@|EzYlKnAwQnARvGnFnKbQ{@jMjCnZfJve@fJg@bLoFz@zE~H~CnFbLfO|E~MqFvB_DfEf@nPzObBdLkCvo@"
        },
        "max_speed": 8.8,
        "moving_time": 2304,
        "name": "Afternoon Ride",
        "photo_count": 0,
        "pr_count": 0,
        "private": false,
        "resource_state": 2,
        "start_date": "2013-09-03T14:02:49Z",
        "start_date_local": "2013-09-03T16:02:49Z",
        "start_latitude": 54.53,
        "start_latlng": [
            54.53,
            18.53
        ],
        "start_longitude": 18.53,
        "timezone": "(GMT+01:00) Europe/Warsaw",
        "total_elevation_gain": 166.8,
        "total_photo_count": 0,
        "trainer": false,
        "type": "Ride",
        "upload_id": 86821172,
        "utc_offset": 7200.0,
        "workout_type": null
    },
    {
        "achievement_count": 0,
        "athlete": {
            "id": 2777656,
            "resource_state": 1
        },
        "athlete_count": 1,
        "average_speed": 5.062,
        "average_watts": 57.6,
        "comment_count": 0,
        "commute": false,
        "device_watts": false,
        "distance": 10401.7,
        "elapsed_time": 2055,
        "elev_high": 122.2,
        "elev_low": -0.9,
        "end_latlng": [
            54.53,
            18.54
        ],
        "external_id": "02c849debc7fa0fc6268ce17ac9a8542",
        "flagged": false,
        "from_accepted_tag": false,
        "gear_id": null,
        "has_heartrate": false,
        "has_kudoed": false,
        "id": 79898664,
        "kilojoules": 118.4,
        "kudos_count": 0,
        "location_city": "Gdynia",
        "location_country": "Poland",
        "location_state": "Pomeranian Voivodeship",
        "manual": false,
        "map": {
            "id": "a79898664",
            "resource_state": 2,
            "summary_polyline": "clokIkd{oBkHpP{OdO{OoFsNaQgEiJ?kRvLce@vG{r@{@gOsI_g@wBc[f@cLoKiRgJeGwBjMsDpAsS_I?aDwB{@gw@cGgJkCSiH_IUf@_NsjAo_@kHjCcVoF_SfJcBvB?jCnK~a@"
        },
        "max_speed": 12.8,
        "moving_time": 2055,
        "name": "Morning Ride",
        "photo_count": 0,
        "pr_count": 0,
        "private": false,
        "resource_state": 2,
        "start_date": "2013-09-04T04:58:01Z",
        "start_date_local": "2013-09-04T06:58:01Z",
        "start_latitude": 54.47,
        "start_latlng": [
            54.47,
            18.49
        ],
        "start_longitude": 18.49,
        "timezone": "(GMT+01:00) Europe/Warsaw",
        "total_elevation_gain": 13.2,
        "total_photo_count": 0,
        "trainer": false,
        "type": "Ride",
        "upload_id": 87015033,
        "utc_offset": 7200.0,
        "workout_type": null
    },
    {
        "achievement_count": 1,
        "athlete": {
            "id": 2777656,
            "resource_state": 1
        },
        "athlete_count": 1,
        "average_speed": 4.834,
        "average_watts": 74.0,
        "comment_count": 0,
        "commute": false,
        "device_watts": false,
        "distance": 13028.6,
        "elapsed_time": 2894,
        "elev_high": 59.8,
        "elev_low": -1.1,
        "end_latlng": [
            54.43,
            18.56
        ],
        "external_id": "0ad18224b2d02d43ff810891b24418fb",
        "flagged": false,
        "from_accepted_tag": false,
        "gear_id": null,
        "has_heartrate": false,
        "has_kudoed": false,
        "id": 79986013,
        "kilojoules": 199.3,
        "kudos_count": 0,
        "location_city": "Gdynia",
        "location_country": "Poland",
        "location_state": "Pomeranian Voivodeship",
        "manual": false,
        "map": {
            "id": "a79986013",
            "resource_state": 2,
            "summary_polyline": "khykIcvcpB{EgTrDgEbLcB~CsDzJzEj\\?faAv[RtDfJx@g@~CnFg@RlCr]yBby@{Tzm@{c@nUm_@nPuIz^sDjCgEjHkC~RcBzh@hJzc@eLn_@vGzJkM~HRfEzE~p@_Ijf@mPvGuInF~C~Hg@{@bLRzJnFh@"
        },
        "max_speed": 9.1,
        "moving_time": 2695,
        "name": "Afternoon Ride",
        "photo_count": 0,
        "pr_count": 1,
        "private": false,
        "resource_state": 2,
        "start_date": "2013-09-04T14:10:31Z",
        "start_date_local": "2013-09-04T16:10:31Z",
        "start_latitude": 54.53,
        "start_latlng": [
            54.53,
            18.54
        ],
        "start_longitude": 18.54,
        "timezone": "(GMT+01:00) Europe/Warsaw",
        "total_elevation_gain": 101.6,
        "total_photo_count": 0,
        "trainer": false,
        "type": "Ride",
        "upload_id": 87107590,
        "utc_offset": 7200.0,
        "workout_type": null
    },
    {
        "achievement_count": 0,
        "athlete": {
            "id": 2777656,
            "resource_state": 1
        },
        "athlete_count": 1,
        "average_speed": 6.528,
        "average_watts": 80.9,
        "comment_count": 0,
        "commute": false,
        "device_watts": false,
        "distance": 10373.4,
        "elapsed_time": 1613,
        "elev_high": 122.5,
        "elev_low": -1.0,
        "end_latlng": [
            54.53,
            18.54
        ],
        "external_id": "0a969aed5f97e39794537678ce587d2b",
        "flagged": false,
        "from_accepted_tag": false,
        "gear_id": null,
        "has_heartrate": false,
        "has_kudoed": false,
        "id": 80171067,
        "kilojoules": 128.5,
        "kudos_count": 0,
        "location_city": "Gdynia",
        "location_country": "Poland",
        "location_state": "Pomeranian Voivodeship",
        "manual": false,
        "map": {
            "id": "a80171067",
            "resource_state": 2,
            "summary_polyline": "clokIcc{oB{EjMwGhJoKxE{OkH_SoZoAkHf@sSbGw[fJc[jCwVoKku@wBaVf@kRcQeVgEcBwB|O_XsIoA}E_v@{EkMsDSiH_IUf@_NccAq]_Xx@wLoFwQvGgEbGnKve@"
        },
        "max_speed": 11.9,
        "moving_time": 1589,
        "name": "Morning Ride",
        "photo_count": 0,
        "pr_count": 0,
        "private": false,
        "resource_state": 2,
        "start_date": "2013-09-05T04:55:42Z",
        "start_date_local": "2013-09-05T06:55:42Z",
        "start_latitude": 54.47,
        "start_latlng": [
            54.47,
            18.49
        ],
        "start_longitude": 18.49,
        "timezone": "(GMT+01:00) Europe/Warsaw",
        "total_elevation_gain": 17.1,
        "total_photo_count": 0,
        "trainer": false,
        "type": "Ride",
        "upload_id": 87302925,
        "utc_offset": 7200.0,
        "workout_type": null
    },
    {
        "achievement_count": 0,
        "athlete": {
            "id": 2777656,
            "resource_state": 1
        },
        "athlete_count": 1,
        "average_speed": 4.727,
        "average_watts": 105.1,
        "comment_count": 0,
        "commute": false,
        "device_watts": false,
        "distance": 10734.2,
        "elapsed_time": 3170,
        "elev_high": 122.9,
        "elev_low": -1.1,
        "end_latlng": [
            54.47,
            18.49
        ],
        "external_id": "9422abcde1bb8703ef57eabc4d2862fb",
        "flagged": false,
        "from_accepted_tag": false,
        "gear_id": null,
        "has_heartrate": false,
        "has_kudoed": false,
        "id": 80254316,
        "kilojoules": 238.8,
        "kudos_count": 0,
        "location_city": "Gdynia",
        "location_country": "Poland",
        "location_state": "Pomeranian Voivodeship",
        "manual": false,
        "map": {
            "id": "a80254316",
            "resource_state": 2,
            "summary_polyline": "{`ykIcbcpB_Nsg@fEgEnKcBrDgEzJfEv[?nbAv[{@~MrITnA~HzO`G~p@jCz@hEfYdJbBgOvBRjRdV?jRjCd^jHz^fOcBvGsDf@zE~HvBjH~M~MhEjR}JjCRvQzOnAzESjMrDS_D|@wBve@"
        },
        "max_speed": 9.9,
        "moving_time": 2271,
        "name": "Afternoon Ride",
        "photo_count": 0,
        "pr_count": 0,
        "private": false,
        "resource_state": 2,
        "start_date": "2013-09-05T14:02:30Z",
        "start_date_local": "2013-09-05T16:02:30Z",
        "start_latitude": 54.53,
        "start_latlng": [
            54.53,
            18.53
        ],
        "start_longitude": 18.53,
        "timezone": "(GMT+01:00) Europe/Warsaw",
        "total_elevation_gain": 163.3,
        "total_photo_count": 0,
        "trainer": false,
        "type": "Ride",
        "upload_id": 87391060,
        "utc_offset": 7200.0,
        "workout_type": null
    },
    {
        "achievement_count": 2,
        "athlete": {
            "id": 2777656,
            "resource_state": 1
        },
        "athlete_count": 1,
        "average_speed": 5.935,
        "average_watts": 117.4,
        "comment_count": 0,
        "commute": false,
        "device_watts": false,
        "distance": 18404.1,
        "elapsed_time": 5296,
        "elev_high": 127.0,
        "elev_low": 26.2,
        "end_latlng": [
            54.47,
            18.49
        ],
        "external_id": "9f55ce07d31c2afa569b1d4cde9dd5c7",
        "flagged": false,
        "from_accepted_tag": false,
        "gear_id": null,
        "has_heartrate": false,
        "has_kudoed": false,
        "id": 80294768,
        "kilojoules": 364.0,
        "kudos_count": 0,
        "location_city": "Gdynia",
        "location_country": "Poland",
        "location_state": "Pomeranian Voivodeship",
        "manual": false,
        "map": {
            "id": "a80294768",
            "resource_state": 2,
            "summary_polyline": "gsmkIoj|oBjCip@{@uI_g@_g@c[ypAoFeLcVja@?gJkM?kHcG{EsIR_IsIwGgEtb@{Oli@{@r]cG~McBnKsScQwBRcLcVgJ_IsNgY{@}dAz@jHnP`G~p@jCf@|EzYpIfEoZjHbGS~H~CjHfJ~HjM??rIbVka@zEpKb[`rArg@lf@f@~HwBbo@"
        },
        "max_speed": 12.3,
        "moving_time": 3101,
        "name": "Evening Ride",
        "photo_count": 0,
        "pr_count": 1,
        "private": false,
        "resource_state": 2,
        "start_date": "2013-09-05T16:13:12Z",
        "start_date_local": "2013-09-05T18:13:12Z",
        "start_latitude": 54.47,
        "start_latlng": [
            54.47,
            18.49
        ],
        "start_longitude": 18.49,
        "timezone": "(GMT+01:00) Europe/Warsaw",
        "total_elevation_gain": 262.9,
        "total_photo_count": 0,
        "trainer": false,
        "type": "Ride",
        "upload_id": 87433316,
        "utc_offset": 7200.0,
        "workout_type": null
    },
    {
        "achievement_count": 0,
        "athlete": {
            "id": 2777656,
            "resource_state": 1
        },
        "athlete_count": 1,
        "average_speed": 6.907,
        "average_watts": 85.0,
        "comment_count": 0,
        "commute": false,
        "device_watts": false,
        "distance": 10837.6,
        "elapsed_time": 1594,
        "elev_high": 124.9,
        "elev_low": -1.0,
        "end_latlng": [
            54.53,
            18.54
        ],
        "external_id": "f1e5b0ef8934de109edea6c3cfc9e93c",
        "flagged": false,
        "from_accepted_tag": false,
        "gear_id": null,
        "has_heartrate": false,
        "has_kudoed": false,
        "id": 80423398,
        "kilojoules": 133.4,
        "kudos_count": 0,
        "location_city": "Gdynia",
        "location_country": "Poland",
        "location_state": "Pomeranian Voivodeship",
        "manual": false,
        "map": {
            "id": "a80423398",
            "resource_state": 2,
            "summary_polyline": "gsmkIoj|oBjCip@g@_Isg@ag@w[urAoFqK{T~a@SsIkMSsIkH_D}HRmH_IwGRwG{^f@oAnPkp@_DkRsDf@{@wBiHkHUf@_NccA_]_XRkM{EkC`DwLtBsDnFbLjf@"
        },
        "max_speed": 12.8,
        "moving_time": 1569,
        "name": "Morning Ride",
        "photo_count": 0,
        "pr_count": 0,
        "private": false,
        "resource_state": 2,
        "start_date": "2013-09-06T04:56:08Z",
        "start_date_local": "2013-09-06T06:56:08Z",
        "start_latitude": 54.47,
        "start_latlng": [
            54.47,
            18.49
        ],
        "start_longitude": 18.49,
        "timezone": "(GMT+01:00) Europe/Warsaw",
        "total_elevation_gain": 30.2,
        "total_photo_count": 0,
        "trainer": false,
        "type": "Ride",
        "upload_id": 87570133,
        "utc_offset": 7200.0,
        "workout_type": null
    },
    {
        "achievement_count": 1,
        "athlete": {
            "id": 2777656,
            "resource_state": 1
        },
        "athlete_count": 1,
        "average_speed": 6.426,
        "average_watts": 137.9,
        "comment_count": 0,
        "commute": false,
        "device_watts": false,
        "distance": 19798.7,
        "elapsed_time": 3303,
        "elev_high": 164.9,
        "elev_low": -1.0,
        "end_latlng": [
            54.47,
            18.49
        ],
        "external_id": "48c5f5e9958b688c849acf2678a54a65",
        "flagged": false,
        "from_accepted_tag": false,
        "gear_id": null,
        "has_heartrate": false,
        "has_kudoed": false,
        "id": 80492973,
        "kilojoules": 425.0,
        "kudos_count": 0,
        "location_city": "Gdynia",
        "location_country": "Poland",
        "location_state": "Pomeranian Voivodeship",
        "manual": false,
        "map": {
            "id": "a80492973",
            "resource_state": 2,
            "summary_polyline": "cbykI{ecpBwL{c@fE{EbLcB~CgEzJzEnZ?~dA~\\fEyh@fOdJfJz@rIzJfTyEnUlFrNeEzEpl@cGrg@sNve@{@n_@oFxLoKto@bBnx@g@ju@cGffA_DjxAbBtg@oAdc@bLxmAsDd^rInK~WnFzExV~M`GzJ_NrXs`AbLnAnFod@RsSrIcLjMo_@Rka@~HoPzE_S?{EcGg^SoKjRql@~CqU"
        },
        "max_speed": 15.8,
        "moving_time": 3081,
        "name": "Afternoon Ride",
        "photo_count": 0,
        "pr_count": 1,
        "private": false,
        "resource_state": 2,
        "start_date": "2013-09-06T14:03:46Z",
        "start_date_local": "2013-09-06T16:03:46Z",
        "start_latitude": 54.53,
        "start_latlng": [
            54.53,
            18.54
        ],
        "start_longitude": 18.54,
        "timezone": "(GMT+01:00) Europe/Warsaw",
        "total_elevation_gain": 254.8,
        "total_photo_count": 0,
        "trainer": false,
        "type": "Ride",
        "upload_id": 87644865,
        "utc_offset": 7200.0,
        "workout_type": null
    },
    {
        "achievement_count": 13,
        "athlete": {
            "id": 2777656,
            "resource_state": 1
        },
        "athlete_count": 3,
        "average_speed": 8.094,
        "average_watts": 171.3,
        "comment_count": 0,
        "commute": false,
        "device_watts": false,
        "distance": 132504.0,
        "elapsed_time": 16979,
        "elev_high": 243.8,
        "elev_low": 0.5,
        "end_latlng": [
            54.52,
            18.55
        ],
        "external_id": "e1dca7c19996de23911ab6ae8c2bafd8",
        "flagged": false,
        "from_accepted_tag": false,
        "gear_id": null,
        "has_heartrate": false,
        "has_kudoed": false,
        "id": 80958159,
        "kilojoules": 2804.5,
        "kudos_count": 0,
        "location_city": "Gdynia",
        "location_country": "Poland",
        "location_state": "Pomeranian Voivodeship",
        "manual": false,
        "map": {
            "id": "a80958159",
            "resource_state": 2,
            "summary_polyline": "wfwkI{nfpBg@f|@~z@fYnF{h@n`BlRbGdm@_l@zjDoKrrGjHfyDrv@lu@gkAthA_q@`fC_DtVnZxj@bGl}@jiAngArl@x|Avj@xOvhA_Nns@wo@~W~HzOjbB~WoFfc@gw@vo@g@jp@rhB~nAnx@~\\f}Bf^be@bxC|YsyAlgFod@jcDrSoFvVrjAnPp`BgEhnA~RfpAn_@kWnn@~f@bhAwQj\\fc@cBb|AwVbcArl@~Hr{@nx@cGbcAjWreF_Ivj@fYns@sIrcB~MxsC{kAyt@_aCkRku@bo@wmAnP_Nzh@seA{w@oZjp@_]bLgzAgO_v@yr@{@qUknAj\\kf@soAcL_~AsdDqlJw[m`Cgr@c~@wBwdCrq@khDbGsoAgw@oKojBns@_Xkp@_aC}nAwy@gkAk\\Sk}AyaBf@}a@nbAm_Ab`@f@ziBoaDbpBzh@zw@ut@ns@yjEvy@w`@ns@mbA_l@m}AchA_eAwGu~@gYyj@vt@__DrjAuhAsv@yt@cGooBfJw{Ifm@opD_Ioi@{_BcQoFzh@kz@sXnA_oAoA|Y"
        },
        "max_speed": 16.5,
        "moving_time": 16370,
        "name": "Morning Ride",
        "photo_count": 0,
        "pr_count": 9,
        "private": false,
        "resource_state": 2,
        "start_date": "2013-09-08T08:13:32Z",
        "start_date_local": "2013-09-08T10:13:32Z",
        "start_latitude": 54.52,
        "start_latlng": [
            54.52,
            18.55
        ],
        "start_longitude": 18.55,
        "timezone": "(GMT+01:00) Europe/Warsaw",
        "total_elevation_gain": 1183.4,
        "total_photo_count": 0,
        "trainer": false,
        "type": "Ride",
        "upload_id": 88143726,
        "utc_offset": 7200.0,
        "workout_type": null
    }
]
